{"cameraMode":{"drawMode":0,"name":"Shaded","section":"Shading Mode"},"sceneLighting":true,"audioPlay":false,"sceneViewState":{"showFog":true,"showMaterialUpdate":false,"showSkybox":true,"showFlares":true,"showImageEffects":true,"showParticleSystems":true},"in2DMode":false,"pivot":{"x":373.324462890625,"y":282.752685546875,"z":-0.26214599609375},"rotation":{"x":0.004189310595393181,"y":0.023095039650797845,"z":0.00009639808558858931,"w":-0.999728798866272},"size":170.63845825195313,"orthographic":false}